{
	"version": "0.3.22", 
	"suite": "unknown_suite", 
	"function_id": 100, 
	"function_name": "ManyAffine", 
	"maximization": false, 
	"algorithm": {"name": "EnhancedAntColonyOptimization", "info": "algorithm_info"},
	"attributes": ["evaluations", "raw_y"],
	"scenarios": [
		{"dimension": 5,
		"path": "data_f100_ManyAffine/IOHprofiler_f100_DIM5.dat",
		"runs": [
			{"instance": 7, "evals": 10000, "best": {"evals": 9214, "y": 0.16219231101095735, "x": [1.4693006807347715, 2.110307842331249, 3.2919549634311256, -1.3274218463310723, 2.198483195595031]}}
		]}
	]
}
