{
	"version": "0.3.22", 
	"suite": "unknown_suite", 
	"function_id": 100, 
	"function_name": "ManyAffine", 
	"maximization": false, 
	"algorithm": {"name": "SocialForagingOptimization", "info": "algorithm_info"},
	"attributes": ["evaluations", "raw_y"],
	"scenarios": [
		{"dimension": 5,
		"path": "data_f100_ManyAffine/IOHprofiler_f100_DIM5.dat",
		"runs": [
			{"instance": 2, "evals": 5000, "best": {"evals": 4798, "y": 0.04414005585696609, "x": [0.6401971271389482, -2.094515072922631, -0.0051996541822255105, 0.7947954656906675, 0.4289463221818766]}}
		]}
	]
}
