{
	"version": "0.3.22", 
	"suite": "unknown_suite", 
	"function_id": 100, 
	"function_name": "ManyAffine", 
	"maximization": false, 
	"algorithm": {"name": "RingTopologyAdaptiveAntColonyOptimization", "info": "algorithm_info"},
	"attributes": ["evaluations", "raw_y"],
	"scenarios": [
		{"dimension": 5,
		"path": "data_f100_ManyAffine/IOHprofiler_f100_DIM5.dat",
		"runs": [
			{"instance": 0, "evals": 10000, "best": {"evals": 9507, "y": 2.9944153846460666, "x": [0.9428442897093376, -1.284315075235798, -0.4021262354920434, -4.348647642587591, -5]}}
		]}
	]
}
